hubx2_mcp_server.py
hubx2_mcp_server-0.1.2.dist-info/METADATA
hubx2_mcp_server-0.1.2.dist-info/WHEEL
hubx2_mcp_server-0.1.2.dist-info/entry_points.txt
hubx2_mcp_server-0.1.2.dist-info/top_level.txt
hubx2_mcp_server-0.1.2.dist-info/RECORD
