Metadata-Version: 2.4
Name: hubx2-mcp-server
Version: 0.1.2
Summary: hubx2's mcp server
Requires-Python: >=3.12
Requires-Dist: mcp>=1.6.0
Requires-Dist: requests>=2.32.3
